{
  "id": "date-time-adapter",
  "name": "DateTime Adapter",
  "description": "A Date & Time adapter to create more advanced rules using sunrise, sunset, weekends, etc.",
  "author": "tomasy",
  "homepage_url": "https://github.com/wfahle/date-time-adapter",
  "license_url": "https://raw.githubusercontent.com/wfahle/date-time-adapter/master/LICENSE",
  "primary_type": "adapter",
  "packages": [
    {
      "architecture": "linux-arm64",
      "language": {
        "name": "python",
        "versions": [
          "3.7"
        ]
      },
      "version": "1.1.1",
      "url": "https://github.com/WTIOAddons/date-time-adapter/releases/download/v1.1.1/date-time-adapter-1.1.1-linux-arm64-v3.7.tgz",
      "checksum": "eadb86a8f982bf3327756600f09e0525ed143833bf6f5aea88016fa62a858d3a",
      "api": {
        "min": 2,
        "max": 2
      },
      "gateway": {
        "min": "0.10.0",
        "max": "*"
      }
    },
    {
      "architecture": "linux-arm64",
      "language": {
        "name": "python",
        "versions": [
          "3.8"
        ]
      },
      "version": "1.1.1",
      "url": "https://github.com/WTIOAddons/date-time-adapter/releases/download/v1.1.1/date-time-adapter-1.1.1-linux-arm64-v3.8.tgz",
      "checksum": "1ea3ba3949f733471f44439f1d5fcc640f66c15ccf918e269a022bdea93b6ac8",
      "api": {
        "min": 2,
        "max": 2
      },
      "gateway": {
        "min": "0.10.0",
        "max": "*"
      }
    },
    {
      "architecture": "linux-arm64",
      "language": {
        "name": "python",
        "versions": [
          "3.9"
        ]
      },
      "version": "1.1.1",
      "url": "https://github.com/WTIOAddons/date-time-adapter/releases/download/v1.1.1/date-time-adapter-1.1.1-linux-arm64-v3.9.tgz",
      "checksum": "b5a48f56cbae1be307367a08aaad7963355547aa96ce1b95ed4169ae8de970b8",
      "api": {
        "min": 2,
        "max": 2
      },
      "gateway": {
        "min": "0.10.0",
        "max": "*"
      }
    },
    {
      "architecture": "linux-arm",
      "language": {
        "name": "python",
        "versions": [
          "3.7"
        ]
      },
      "version": "1.1.1",
      "url": "https://github.com/WTIOAddons/date-time-adapter/releases/download/v1.1.1/date-time-adapter-1.1.1-linux-arm-v3.7.tgz",
      "checksum": "5581b340ab01594d6e64e7799b8f6961b967f1797061f945527c724c0f389772",
      "api": {
        "min": 2,
        "max": 2
      },
      "gateway": {
        "min": "0.10.0",
        "max": "*"
      }
    },
    {
      "architecture": "linux-arm",
      "language": {
        "name": "python",
        "versions": [
          "3.8"
        ]
      },
      "version": "1.1.1",
      "url": "https://github.com/WTIOAddons/date-time-adapter/releases/download/v1.1.1/date-time-adapter-1.1.1-linux-arm-v3.8.tgz",
      "checksum": "a0cc6c32eed9fceb2af2340a9d46fcb0b2947bd27d50ed3935cee3ccdb14e67a",
      "api": {
        "min": 2,
        "max": 2
      },
      "gateway": {
        "min": "0.10.0",
        "max": "*"
      }
    },
    {
      "architecture": "linux-arm",
      "language": {
        "name": "python",
        "versions": [
          "3.9"
        ]
      },
      "version": "1.1.1",
      "url": "https://github.com/WTIOAddons/date-time-adapter/releases/download/v1.1.1/date-time-adapter-1.1.1-linux-arm-v3.9.tgz",
      "checksum": "3c8956f932457f44b785761ebf357448e569069ec3832f8b7260ce26ee530dbd",
      "api": {
        "min": 2,
        "max": 2
      },
      "gateway": {
        "min": "0.10.0",
        "max": "*"
      }
    },
    {
      "architecture": "linux-x64",
      "language": {
        "name": "python",
        "versions": [
          "3.7"
        ]
      },
      "version": "1.1.1",
      "url": "https://github.com/WTIOAddons/date-time-adapter/releases/download/v1.1.1/date-time-adapter-1.1.1-linux-x64-v3.7.tgz",
      "checksum": "a863f589b9ab050c3f3891c9d075eaee0bd372df970ed5f3aafd1b61855dfeac",
      "api": {
        "min": 2,
        "max": 2
      },
      "gateway": {
        "min": "0.10.0",
        "max": "*"
      }
    },
    {
      "architecture": "linux-x64",
      "language": {
        "name": "python",
        "versions": [
          "3.8"
        ]
      },
      "version": "1.1.1",
      "url": "https://github.com/WTIOAddons/date-time-adapter/releases/download/v1.1.1/date-time-adapter-1.1.1-linux-x64-v3.8.tgz",
      "checksum": "9a7fabbb4f1e6c4bc047011477af6227cd547ceead34f54ff327188bce175e04",
      "api": {
        "min": 2,
        "max": 2
      },
      "gateway": {
        "min": "0.10.0",
        "max": "*"
      }
    },
    {
      "architecture": "linux-x64",
      "language": {
        "name": "python",
        "versions": [
          "3.9"
        ]
      },
      "version": "1.1.1",
      "url": "https://github.com/WTIOAddons/date-time-adapter/releases/download/v1.1.1/date-time-adapter-1.1.1-linux-x64-v3.9.tgz",
      "checksum": "8a3d69d94d4822b4cb4170ff47cb5e8365cdefc623115b9dc02443727b92814e",
      "api": {
        "min": 2,
        "max": 2
      },
      "gateway": {
        "min": "0.10.0",
        "max": "*"
      }
    },
    {
      "architecture": "darwin-x64",
      "language": {
        "name": "python",
        "versions": [
          "3.7"
        ]
      },
      "version": "1.1.1",
      "url": "https://github.com/WTIOAddons/date-time-adapter/releases/download/v1.1.1/date-time-adapter-1.1.1-darwin-x64-v3.7.tgz",
      "checksum": "b9636cb82a005d3f668e6b35c149c0bfadd319bb429b1503d2a336b1aa6d909f",
      "api": {
        "min": 2,
        "max": 2
      },
      "gateway": {
        "min": "0.10.0",
        "max": "*"
      }
    },
    {
      "architecture": "darwin-x64",
      "language": {
        "name": "python",
        "versions": [
          "3.8"
        ]
      },
      "version": "1.1.1",
      "url": "https://github.com/WTIOAddons/date-time-adapter/releases/download/v1.1.1/date-time-adapter-1.1.1-darwin-x64-v3.8.tgz",
      "checksum": "a3e001c072f10589da5489611016b9ec230ce6712d6d5bd5d8fed797a8c886b4",
      "api": {
        "min": 2,
        "max": 2
      },
      "gateway": {
        "min": "0.10.0",
        "max": "*"
      }
    },
    {
      "architecture": "darwin-x64",
      "language": {
        "name": "python",
        "versions": [
          "3.9"
        ]
      },
      "version": "1.1.1",
      "url": "https://github.com/WTIOAddons/date-time-adapter/releases/download/v1.1.1/date-time-adapter-1.1.1-darwin-x64-v3.9.tgz",
      "checksum": "31f88eb12a01b096afba395174c314b5a28d957044a5475b6db0510ee8c90ee5",
      "api": {
        "min": 2,
        "max": 2
      },
      "gateway": {
        "min": "0.10.0",
        "max": "*"
      }
    }
  ]
}