{
  "id": "thing-url-adapter",
  "name": "Web Thing",
  "description": "Native web thing support",
  "author": "Mozilla IoT",
  "homepage_url": "https://github.com/mozilla-iot/thing-url-adapter",
  "license_url": "https://github.com/mozilla-iot/thing-url-adapter/blob/master/LICENSE",
  "primary_type": "adapter",
  "packages": [
    {
      "architecture": "any",
      "language": {
        "name": "nodejs",
        "versions": [
          "any"
        ]
      },
      "version": "0.4.6",
      "url": "https://github.com/mozilla-iot/thing-url-adapter/releases/download/v0.4.6/thing-url-adapter-0.4.6.tgz",
      "checksum": "529c66197bc54a449f5c5502fa949ff6db4ddb208da76c9ee294c1b37a05ed67",
      "api": {
        "min": 2,
        "max": 2
      },
      "gateway": {
        "min": "0.10.0",
        "max": "*"
      }
    }
  ]
}
