{
  "id": "zwave-adapter",
  "name": "Z-Wave",
  "description": "Z-Wave device support",
  "author": "Mozilla IoT",
  "homepage_url": "https://github.com/mozilla-iot/zwave-adapter",
  "license_url": "https://github.com/mozilla-iot/zwave-adapter/blob/master/LICENSE",
  "primary_type": "adapter",
  "packages": [
    {
      "architecture": "linux-arm",
      "language": {
        "name": "nodejs",
        "versions": [
          "57"
        ]
      },
      "version": "0.10.5",
      "url": "https://s3-us-west-2.amazonaws.com/mozilla-gateway-addons/zwave-adapter-0.10.5-linux-arm-v8.tgz",
      "checksum": "43770641d553b92255e43ab804ccc041eb92f5fd661d1493e48cf6870ae2dbbb",
      "api": {
        "min": 2,
        "max": 2
      },
      "gateway": {
        "min": "0.10.0",
        "max": "*"
      }
    },
    {
      "architecture": "linux-arm64",
      "language": {
        "name": "nodejs",
        "versions": [
          "57"
        ]
      },
      "version": "0.10.5",
      "url": "https://s3-us-west-2.amazonaws.com/mozilla-gateway-addons/zwave-adapter-0.10.5-linux-arm64-v8.tgz",
      "checksum": "fd23e535daab7c264aeaf1a3d8dd7cc8f4f3bc17e11fdb5c04fb92636c3a0e4c",
      "api": {
        "min": 2,
        "max": 2
      },
      "gateway": {
        "min": "0.10.0",
        "max": "*"
      }
    },
    {
      "architecture": "linux-x64",
      "language": {
        "name": "nodejs",
        "versions": [
          "57"
        ]
      },
      "version": "0.10.5",
      "url": "https://s3-us-west-2.amazonaws.com/mozilla-gateway-addons/zwave-adapter-0.10.5-linux-x64-v8.tgz",
      "checksum": "287eae27ec1bf7d641cd97b05f5796a22544c458ed5e2f2d10e1e124db3c220a",
      "api": {
        "min": 2,
        "max": 2
      },
      "gateway": {
        "min": "0.10.0",
        "max": "*"
      }
    },
    {
      "architecture": "darwin-x64",
      "language": {
        "name": "nodejs",
        "versions": [
          "57"
        ]
      },
      "version": "0.10.5",
      "url": "https://s3-us-west-2.amazonaws.com/mozilla-gateway-addons/zwave-adapter-0.10.5-darwin-x64-v8.tgz",
      "checksum": "3aae69869d51ad00efb513d07acc6f9224286e1b57dc2ef1dbe54888b7fbf4ec",
      "api": {
        "min": 2,
        "max": 2
      },
      "gateway": {
        "min": "0.10.0",
        "max": "*"
      }
    },
    {
      "architecture": "linux-arm",
      "language": {
        "name": "nodejs",
        "versions": [
          "64"
        ]
      },
      "version": "0.10.5",
      "url": "https://s3-us-west-2.amazonaws.com/mozilla-gateway-addons/zwave-adapter-0.10.5-linux-arm-v10.tgz",
      "checksum": "3073b6b9a3b217da329297e704348d3a2b9270384f6ef3e64ba2f27236dc4240",
      "api": {
        "min": 2,
        "max": 2
      },
      "gateway": {
        "min": "0.10.0",
        "max": "*"
      }
    },
    {
      "architecture": "linux-arm64",
      "language": {
        "name": "nodejs",
        "versions": [
          "64"
        ]
      },
      "version": "0.10.5",
      "url": "https://s3-us-west-2.amazonaws.com/mozilla-gateway-addons/zwave-adapter-0.10.5-linux-arm64-v10.tgz",
      "checksum": "79f1b8ff7a99d298cf3acb543684c6f6013ee2d2197252a68c4e4f2a51b53997",
      "api": {
        "min": 2,
        "max": 2
      },
      "gateway": {
        "min": "0.10.0",
        "max": "*"
      }
    },
    {
      "architecture": "linux-x64",
      "language": {
        "name": "nodejs",
        "versions": [
          "64"
        ]
      },
      "version": "0.10.5",
      "url": "https://s3-us-west-2.amazonaws.com/mozilla-gateway-addons/zwave-adapter-0.10.5-linux-x64-v10.tgz",
      "checksum": "9a47397f73a7516e4318de59eb460a3cfdd4cfdf7767ef879fdd7b14bc3ef5b3",
      "api": {
        "min": 2,
        "max": 2
      },
      "gateway": {
        "min": "0.10.0",
        "max": "*"
      }
    },
    {
      "architecture": "darwin-x64",
      "language": {
        "name": "nodejs",
        "versions": [
          "64"
        ]
      },
      "version": "0.10.5",
      "url": "https://s3-us-west-2.amazonaws.com/mozilla-gateway-addons/zwave-adapter-0.10.5-darwin-x64-v10.tgz",
      "checksum": "c609597c25aa113ccf2aac9e55b921b66ede8cbcbb48ccacc3c2dcc114aa4069",
      "api": {
        "min": 2,
        "max": 2
      },
      "gateway": {
        "min": "0.10.0",
        "max": "*"
      }
    },
    {
      "architecture": "linux-arm",
      "language": {
        "name": "nodejs",
        "versions": [
          "72"
        ]
      },
      "version": "0.10.5",
      "url": "https://s3-us-west-2.amazonaws.com/mozilla-gateway-addons/zwave-adapter-0.10.5-linux-arm-v12.tgz",
      "checksum": "a2b21e1ef9b98602fd6f7fb1788386a3bca36fa60bf46c11a1cfd1c140a9fe37",
      "api": {
        "min": 2,
        "max": 2
      },
      "gateway": {
        "min": "0.10.0",
        "max": "*"
      }
    },
    {
      "architecture": "linux-arm64",
      "language": {
        "name": "nodejs",
        "versions": [
          "72"
        ]
      },
      "version": "0.10.5",
      "url": "https://s3-us-west-2.amazonaws.com/mozilla-gateway-addons/zwave-adapter-0.10.5-linux-arm64-v12.tgz",
      "checksum": "ddfcfa9cfd033dd9ceac6d98ef0e57d3c9bb2123b28d49e2f58efceefd31cb94",
      "api": {
        "min": 2,
        "max": 2
      },
      "gateway": {
        "min": "0.10.0",
        "max": "*"
      }
    },
    {
      "architecture": "linux-x64",
      "language": {
        "name": "nodejs",
        "versions": [
          "72"
        ]
      },
      "version": "0.10.5",
      "url": "https://s3-us-west-2.amazonaws.com/mozilla-gateway-addons/zwave-adapter-0.10.5-linux-x64-v12.tgz",
      "checksum": "1a23348181db9a75da0c206ecc666033f243395a5dd200f1ceb73ac936eb00b4",
      "api": {
        "min": 2,
        "max": 2
      },
      "gateway": {
        "min": "0.10.0",
        "max": "*"
      }
    },
    {
      "architecture": "darwin-x64",
      "language": {
        "name": "nodejs",
        "versions": [
          "72"
        ]
      },
      "version": "0.10.5",
      "url": "https://s3-us-west-2.amazonaws.com/mozilla-gateway-addons/zwave-adapter-0.10.5-darwin-x64-v12.tgz",
      "checksum": "b9fc774e72da36397db69f90bf1bfcafec2347f881208d63258aa5ca42c088f2",
      "api": {
        "min": 2,
        "max": 2
      },
      "gateway": {
        "min": "0.10.0",
        "max": "*"
      }
    }
  ]
}
